azure_ext.py
azure_arm_nb_extensions-0.0.2.dist-info/METADATA
azure_arm_nb_extensions-0.0.2.dist-info/WHEEL
azure_arm_nb_extensions-0.0.2.dist-info/top_level.txt
azure_arm_nb_extensions-0.0.2.dist-info/RECORD
