Metadata-Version: 2.1
Name: azure-arm-nb-extensions
Version: 0.0.2
Summary: Jupyter notebook extensions for azure arm.
Home-page: https://github.com/horietakehiro/azure-arm-nb-extensions
Author: Takehiro Horie
Author-email: horie.takehiro@outlook.jp
License: MIT License
Platform: UNKNOWN
Classifier: Programming Language :: Python :: 3.8
Classifier: Operating System :: OS Independent
Requires-Python: >=3.8
Requires-Dist: argon2-cffi (==21.3.0)
Requires-Dist: argon2-cffi-bindings (==21.2.0)
Requires-Dist: asttokens (==2.0.5)
Requires-Dist: attrs (==21.4.0)
Requires-Dist: backcall (==0.2.0)
Requires-Dist: beautifulsoup4 (==4.11.1)
Requires-Dist: bleach (==5.0.1)
Requires-Dist: cffi (==1.15.1)
Requires-Dist: debugpy (==1.6.2)
Requires-Dist: decorator (==5.1.1)
Requires-Dist: defusedxml (==0.7.1)
Requires-Dist: entrypoints (==0.4)
Requires-Dist: executing (==0.9.0)
Requires-Dist: fastjsonschema (==2.16.1)
Requires-Dist: importlib-resources (==5.9.0)
Requires-Dist: ipykernel (==6.15.1)
Requires-Dist: ipython (==8.4.0)
Requires-Dist: ipython-genutils (==0.2.0)
Requires-Dist: ipywidgets (==7.7.1)
Requires-Dist: jedi (==0.18.1)
Requires-Dist: Jinja2 (==3.1.2)
Requires-Dist: json5 (==0.9.8)
Requires-Dist: jsonschema (==4.7.2)
Requires-Dist: jupyter-client (==7.3.4)
Requires-Dist: jupyter-core (==4.11.1)
Requires-Dist: jupyterlab-pygments (==0.2.2)
Requires-Dist: jupyterlab-widgets (==1.1.1)
Requires-Dist: MarkupSafe (==2.1.1)
Requires-Dist: matplotlib-inline (==0.1.3)
Requires-Dist: mistune (==0.8.4)
Requires-Dist: nbclient (==0.6.6)
Requires-Dist: nbconvert (==6.5.0)
Requires-Dist: nbformat (==5.4.0)
Requires-Dist: nest-asyncio (==1.5.5)
Requires-Dist: notebook (==6.4.12)
Requires-Dist: packaging (==21.3)
Requires-Dist: pandocfilters (==1.5.0)
Requires-Dist: parso (==0.8.3)
Requires-Dist: pexpect (==4.8.0)
Requires-Dist: pickleshare (==0.7.5)
Requires-Dist: pip (==20.2.3)
Requires-Dist: prometheus-client (==0.14.1)
Requires-Dist: prompt-toolkit (==3.0.30)
Requires-Dist: psutil (==5.9.1)
Requires-Dist: ptyprocess (==0.7.0)
Requires-Dist: pure-eval (==0.2.2)
Requires-Dist: pycparser (==2.21)
Requires-Dist: Pygments (==2.12.0)
Requires-Dist: pyparsing (==3.0.9)
Requires-Dist: pyrsistent (==0.18.1)
Requires-Dist: python-dateutil (==2.8.2)
Requires-Dist: pyzmq (==23.2.0)
Requires-Dist: Send2Trash (==1.8.0)
Requires-Dist: setuptools (==49.2.1)
Requires-Dist: six (==1.16.0)
Requires-Dist: soupsieve (==2.3.2.post1)
Requires-Dist: stack-data (==0.3.0)
Requires-Dist: terminado (==0.15.0)
Requires-Dist: tinycss2 (==1.1.1)
Requires-Dist: tornado (==6.2)
Requires-Dist: traitlets (==5.3.0)
Requires-Dist: wcwidth (==0.2.5)
Requires-Dist: webencodings (==0.5.1)
Requires-Dist: wheel (==0.37.1)
Requires-Dist: widgetsnbextension (==3.6.1)
Requires-Dist: zipp (==3.8.1)
